konbinine/__init__.py
konbinine/enums.py
konbinine/exceptions.py
konbinine/fields.py
konbinine/logs.py
konbinine/models.py
konbinine/types.py
konbinine/utils.py
konbinine-0.3.11.dist-info/licenses/LICENSE
konbinine-0.3.11.dist-info/METADATA
konbinine-0.3.11.dist-info/WHEEL
konbinine-0.3.11.dist-info/top_level.txt
konbinine-0.3.11.dist-info/zip-safe
konbinine-0.3.11.dist-info/RECORD
