Metadata-Version: 2.4
Name: konbinine
Version: 0.3.11
Summary: Opinionated Autodesk Shotgun/ShotGrid API Wrapper.
Home-page: https://github.com/hueyyeng/konbini
Author: Huey Yeng
Author-email: Huey Yeng <huey.yeng.mmu@gmail.com>
Maintainer: Huey Yeng
Maintainer-email: Huey Yeng <huey.yeng.mmu@gmail.com>
License: MIT License
Project-URL: Homepage, https://github.com/hueyyeng/konbini
Project-URL: Bug Reports, https://github.com/hueyyeng/konbini/issues
Project-URL: Source, https://github.com/hueyyeng/konbini
Keywords: python,library,shotgrid,shotgun,api,autodesk
Classifier: Intended Audience :: Developers
Classifier: Programming Language :: Python :: 3.11
Classifier: Programming Language :: Python :: 3.10
Classifier: Programming Language :: Python :: 3.9
Classifier: Programming Language :: Python :: 3.8
Classifier: Programming Language :: Python :: 3.7
Classifier: Operating System :: MacOS
Classifier: Operating System :: POSIX :: Linux
Classifier: Operating System :: Microsoft :: Windows :: Windows 10
Requires-Python: >=3.7
License-File: LICENSE
Requires-Dist: shotgun-api3>=3.2.6
Requires-Dist: requests>=2.28.0
Dynamic: license-file
